claim_summarizer/__init__.py
claim_summarizer/main.py
claim_summarizer/prompts.py
claim_summarizer-2025.12.21172911.dist-info/METADATA
claim_summarizer-2025.12.21172911.dist-info/WHEEL
claim_summarizer-2025.12.21172911.dist-info/top_level.txt
claim_summarizer-2025.12.21172911.dist-info/RECORD
