Metadata-Version: 2.4
Name: claim-summarizer
Version: 2025.12.21172911
Summary: A new package that takes user-provided text (such as a blog post title or a short article snippet) and generates a structured summary highlighting key advantages or claims. It uses an LLM to analyze t
Author-email: claim-summarizer <hi@eugene.plus>
License: MIT
Project-URL: Homepage, https://github.com/chigwell/claim-summarizer
Requires-Python: >=3.9
Requires-Dist: langchain-llm7>=0.0.0
Requires-Dist: llmatch-messages>=0.0.0
Requires-Dist: langchain-core>=0.3.0
